MANIFEST.in
README.md
setup.py
fb_tribe.egg-info/PKG-INFO
fb_tribe.egg-info/SOURCES.txt
fb_tribe.egg-info/dependency_links.txt
fb_tribe.egg-info/entry_points.txt
fb_tribe.egg-info/not-zip-safe
fb_tribe.egg-info/requires.txt
fb_tribe.egg-info/top_level.txt
tribe/Tribe.py
tribe/app_secrets